[
  {
    "name": "aiko",
    "usage": 2
  },
  {
    "name": "ping",
    "usage": 1
  },
  {
    "name": "uptime",
    "usage": 1
  },
  {
    "name": "help",
    "usage": 1
  },
  {
    "name": "mi",
    "usage": 1
  },
  {
    "name": "upt",
    "usage": 2
  },
  {
    "name": "stats",
    "usage": 2
  },
  {
    "name": "dcmd",
    "usage": 5
  },
  {
    "name": "upt2",
    "usage": 1
  },
  {
    "name": "gh",
    "usage": 2
  },
  {
    "name": "sing",
    "usage": 2
  },
  {
    "name": "",
    "usage": 3
  },
  {
    "name": "uid",
    "usage": 1
  },
  {
    "name": "bd",
    "usage": 1
  },
  {
    "name": "ms",
    "usage": 1
  },
  {
    "name": "bal",
    "usage": 1
  },
  {
    "name": "roulette",
    "usage": 1
  },
  {
    "name": "slot",
    "usage": 2
  },
  {
    "name": "daily",
    "usage": 1
  }
]