{"100057399829870":{"bank":105001034.305125,"loan":998,"lastInterestClaimed":1717582929959,"loanTakenTime":1717066901781,"loanInterestRate":0.02},"100080195076753":{"bank":1.102500000037253,"loan":0,"lastInterestClaimed":1717266844031,"loanTakenTime":0,"loanInterestRate":0.02},"100041931226770":{"bank":0,"loan":100000,"lastInterestClaimed":0,"loanTakenTime":1717067529190,"loanInterestRate":0.02},"100095607875797":{"bank":3000001,"loan":0,"lastInterestClaimed":0,"loanTakenTime":0,"loanInterestRate":0.02},"100068269416536":{"bank":14546255168.68,"loan":0,"lastInterestClaimed":1717429279311,"loanTakenTime":0,"loanInterestRate":0.02},"100073691126578":{"bank":105,"loan":0,"lastInterestClaimed":1717071113198,"loanTakenTime":0,"loanInterestRate":0.02},"100075454605535":{"bank":1469,"loan":0,"lastInterestClaimed":1717081678739,"loanTakenTime":0,"loanInterestRate":0.02},"100095365990630":{"bank":2748418580.2299995,"loan":0,"lastInterestClaimed":1717429662555,"loanTakenTime":0,"loanInterestRate":0.02},"100042061672382":{"bank":1000000000,"loan":0,"lastInterestClaimed":0,"loanTakenTime":0,"loanInterestRate":0.02},"100062127322485":{"bank":155051050003,"loan":0,"lastInterestClaimed":1717433661649,"loanTakenTime":0,"loanInterestRate":0.02},"100066460973139":{"bank":0.3999999985098839,"loan":0,"lastInterestClaimed":1717563956836,"loanTakenTime":0,"loanInterestRate":0.02},"100092721756618":{"bank":0,"loan":50000,"lastInterestClaimed":1717144075361,"loanTakenTime":1717085734407,"loanInterestRate":0.02},"100089377592600":{"bank":420,"loan":0,"lastInterestClaimed":1717168906376,"loanTakenTime":0,"loanInterestRate":0.02},"61557796831052":{"bank":10025000,"loan":0,"lastInterestClaimed":1717266041139,"loanTakenTime":0,"loanInterestRate":0.02},"100065896770979":{"bank":0,"loan":0,"lastInterestClaimed":0,"loanTakenTime":0,"loanInterestRate":0.02},"100082959835429":{"bank":0,"loan":0,"lastInterestClaimed":0,"loanTakenTime":0,"loanInterestRate":0.02},"61552802462875":{"bank":0,"loan":50000,"lastInterestClaimed":1717144694109,"loanTakenTime":1717144681155,"loanInterestRate":0.02},"100039941250794":{"bank":3828.45,"loan":0,"lastInterestClaimed":1717583315234,"loanTakenTime":0,"loanInterestRate":0.02},"100089814680233":{"bank":0,"loan":0,"lastInterestClaimed":1717159172843,"loanTakenTime":0,"loanInterestRate":0.02},"100078994031538":{"bank":0,"loan":0,"lastInterestClaimed":0,"loanTakenTime":0,"loanInterestRate":0.02},"100091960159667":{"bank":0,"loan":0,"lastInterestClaimed":0,"loanTakenTime":0,"loanInterestRate":0.02},"100091503896878":{"bank":0,"loan":0,"lastInterestClaimed":0,"loanTakenTime":0,"loanInterestRate":0.02},"100095033785033":{"bank":0,"loan":50000,"lastInterestClaimed":0,"loanTakenTime":1717176178229,"loanInterestRate":0.02},"100056194267902":{"bank":0,"loan":0,"lastInterestClaimed":1717475300857,"loanTakenTime":0,"loanInterestRate":0.02},"61557305549568":{"bank":2500,"loan":50000,"lastInterestClaimed":1717218123612,"loanTakenTime":1717218053059,"loanInterestRate":0.02},"100011457600959":{"bank":0,"loan":0,"lastInterestClaimed":0,"loanTakenTime":0,"loanInterestRate":0.02},"100078088600339":{"bank":0,"loan":0,"lastInterestClaimed":0,"loanTakenTime":0,"loanInterestRate":0.02},"61557519455411":{"bank":69,"loan":0,"lastInterestClaimed":1717267262289,"loanTakenTime":0,"loanInterestRate":0.02},"100060532689687":{"bank":0,"loan":0,"lastInterestClaimed":1717275636951,"loanTakenTime":0,"loanInterestRate":0.02},"61558782404128":{"bank":50,"loan":50,"lastInterestClaimed":0,"loanTakenTime":1717287512589,"loanInterestRate":0.02},"100094910061758":{"bank":0,"loan":0,"lastInterestClaimed":0,"loanTakenTime":0,"loanInterestRate":0.02},"61553797076298":{"bank":0,"loan":0,"lastInterestClaimed":0,"loanTakenTime":0,"loanInterestRate":0.02},"100054560899615":{"bank":0,"loan":0,"lastInterestClaimed":1717558362768,"loanTakenTime":0,"loanInterestRate":0.02},"100045759980785":{"bank":10.5,"loan":10,"lastInterestClaimed":1717557656949,"loanTakenTime":1717404543857,"loanInterestRate":0.02},"100010324453972":{"bank":150,"loan":0,"lastInterestClaimed":0,"loanTakenTime":0,"loanInterestRate":0.02},"100079098667665":{"bank":46117500000,"loan":0,"lastInterestClaimed":1717575932890,"loanTakenTime":0,"loanInterestRate":0.02},"100065751612368":{"bank":0,"loan":0,"lastInterestClaimed":1717432051182,"loanTakenTime":0,"loanInterestRate":0.02},"61558303554125":{"bank":0,"loan":50000,"lastInterestClaimed":0,"loanTakenTime":1717501912413,"loanInterestRate":0.02},"100070712751672":{"bank":0,"loan":1000,"lastInterestClaimed":0,"loanTakenTime":1717509284243,"loanInterestRate":0.02},"100050797473760":{"bank":0,"loan":0,"lastInterestClaimed":0,"loanTakenTime":0,"loanInterestRate":0.02},"100020507867702":{"bank":694,"loan":0,"lastInterestClaimed":1717586723500,"loanTakenTime":0,"loanInterestRate":0.02},"61559775127507":{"bank":0,"loan":0,"lastInterestClaimed":0,"loanTakenTime":0,"loanInterestRate":0.02},"100071341284833":{"bank":0,"loan":0,"lastInterestClaimed":0,"loanTakenTime":0,"loanInterestRate":0.02},"100083061953327":{"bank":315,"loan":0,"lastInterestClaimed":1717591544671,"loanTakenTime":0,"loanInterestRate":0.02}}